{
	"configurations" : 
	[
		{
			"directories" : 
			[
				{
					"build" : ".",
					"jsonFile" : "directory-.-Debug-d0094a50bb2071803777.json",
					"minimumCMakeVersion" : 
					{
						"string" : "3.8"
					},
					"projectIndex" : 0,
					"source" : ".",
					"targetIndexes" : 
					[
						0
					]
				}
			],
			"name" : "Debug",
			"projects" : 
			[
				{
					"directoryIndexes" : 
					[
						0
					],
					"name" : "netology_homework_cpp_sql1",
					"targetIndexes" : 
					[
						0
					]
				}
			],
			"targets" : 
			[
				{
					"directoryIndex" : 0,
					"id" : "netology_homework_cpp_sql1::@6890427a1f51a3e7e1df",
					"jsonFile" : "target-netology_homework_cpp_sql1-Debug-357bdf08778e86037eec.json",
					"name" : "netology_homework_cpp_sql1",
					"projectIndex" : 0
				}
			]
		}
	],
	"kind" : "codemodel",
	"paths" : 
	{
		"build" : "C:/Users/dpoli/source/repos/netology_homework_cpp_sql1/out/build/x64-debug",
		"source" : "C:/Users/dpoli/source/repos/netology_homework_cpp_sql1"
	},
	"version" : 
	{
		"major" : 2,
		"minor" : 8
	}
}
